ptv/__init__.py
ptv/base.py
ptv/ptv.py
ptv/v2.py
ptv/v3.py
ptv-0.1.dist-info/DESCRIPTION.rst
ptv-0.1.dist-info/METADATA
ptv-0.1.dist-info/RECORD
ptv-0.1.dist-info/WHEEL
ptv-0.1.dist-info/metadata.json
ptv-0.1.dist-info/top_level.txt
